{
  "id": 10197,
  "num": 381,
  "slug": "latios-mega",
  "name": "Mega Latios",
  "gen": 6,
  "forms": [],
  "isBattleOnly": true,
  "isReversible": true,
  "isGmax": false,
  "formName": "Mega",
  "formSlug": "mega",
  "formOrder": 1,
  "baseSpecies": "latios",
  "dataGen": 8,
  "type1": "dragon",
  "type2": "psychic",
  "eggGroup1": "undiscovered",
  "eggGroup2": null,
  "ability1": "levitate",
  "ability2": null,
  "abilityHidden": null,
  "height": 229,
  "weight": 7000,
  "color": "purple",
  "actualColor": "purple",
  "shape": "wings-single",
  "maleRatio": 100,
  "femaleRatio": 0,
  "growthRate": "slow",
  "catchRate": 3,
  "hatchCycles": 120,
  "baseFriendship": 90,
  "baseStats": {
    "hp": 80,
    "atk": 130,
    "def": 100,
    "spa": 160,
    "spd": 120,
    "spe": 110
  },
  "baseStatsTotal": 700,
  "yieldStats": {
    "hp": 0,
    "atk": 0,
    "def": 0,
    "spa": 3,
    "spd": 0,
    "spe": 0
  },
  "yieldBaseExp": 315,
  "isFemale": false,
  "isCosmetic": false,
  "isLegendary": true,
  "isMythical": false,
  "isFusion": false,
  "isMega": true,
  "isPrimal": false,
  "canDynamax": false,
  "isTotem": false,
  "isAbilityForm": false,
  "isRegional": false,
  "isHomeStorable": false,
  "isHomeRegistrable": true,
  "showdownSlug": "latiosmega",
  "veekunSlug": "latios-mega",
  "veekunFormId": 10165
}
