{
  "id": 744,
  "num": 744,
  "slug": "rockruff",
  "name": "Rockruff",
  "gen": 7,
  "forms": [
    "rockruff-own-tempo"
  ],
  "formName": "Midday",
  "formSlug": "midday",
  "formOrder": 0,
  "baseSpecies": null,
  "baseDataForm": null,
  "imgSprite": "rockruff",
  "imgHome": "0701-0800/0744",
  "dataGen": 8,
  "type1": "rock",
  "type2": null,
  "eggGroup1": "field",
  "eggGroup2": null,
  "ability1": "keen-eye",
  "ability2": "vital-spirit",
  "abilityHidden": "steadfast",
  "height": 50,
  "weight": 919,
  "color": "brown",
  "actualColor": "brown",
  "shape": "quadruped",
  "maleRatio": 0,
  "femaleRatio": 0,
  "growthRate": "medium-fast",
  "catchRate": 190,
  "hatchCycles": 15,
  "baseFriendship": 70,
  "baseStats": {
    "hp": 45,
    "atk": 65,
    "def": 40,
    "spa": 30,
    "spd": 40,
    "spe": 60
  },
  "baseStatsTotal": 280,
  "yieldStats": {
    "hp": 0,
    "atk": 1,
    "def": 0,
    "spa": 0,
    "spd": 0,
    "spe": 0
  },
  "yieldBaseExp": 56,
  "isFemale": false,
  "isCosmetic": false,
  "isLegendary": false,
  "isMythical": false,
  "isFusion": false,
  "isMega": false,
  "isPrimal": false,
  "isGmax": false,
  "canDynamax": true,
  "isTotem": false,
  "isRegional": false,
  "isHomeStorable": true,
  "showdownSlug": "rockruff",
  "veekunSlug": "rockruff",
  "veekunFormId": 744,
  "title": "Rockruff"
}