{
  "id": 10124,
  "num": 201,
  "slug": "unown-o",
  "name": "Unown-O",
  "gen": 2,
  "forms": [],
  "formName": "O",
  "formSlug": "o",
  "formOrder": 14,
  "baseSpecies": "unown",
  "baseDataForm": "unown",
  "imgSprite": "unown-o",
  "imgHome": "0201-0300/0201-o",
  "isFemale": false,
  "isCosmetic": true,
  "isLegendary": false,
  "isMythical": false,
  "isFusion": false,
  "isMega": false,
  "isPrimal": false,
  "isGmax": false,
  "canDynamax": true,
  "isTotem": false,
  "isRegional": false,
  "isHomeStorable": true,
  "showdownSlug": "unown",
  "veekunSlug": "unown-o",
  "veekunFormId": 10014
}
