{
  "id": 10446,
  "num": 869,
  "slug": "alcremie-mint-cream-strawberry",
  "name": "Alcremie (Mint Cream Strawberry)",
  "gen": 8,
  "forms": [],
  "isHomeRegistrable": true,
  "isBattleOnly": false,
  "isReversible": false,
  "isGmax": false,
  "formName": "Mint Cream Strawberry",
  "formSlug": "mint-cream-strawberry",
  "formOrder": 21,
  "baseSpecies": "alcremie",
  "isFemale": false,
  "isCosmetic": true,
  "isLegendary": false,
  "isMythical": false,
  "isFusion": false,
  "isMega": false,
  "isPrimal": false,
  "canDynamax": true,
  "isTotem": false,
  "isAbilityForm": false,
  "isRegional": false,
  "isHomeStorable": true,
  "showdownSlug": "alcremie",
  "veekunSlug": "alcremie-mint-cream",
  "veekunFormId": 10348
}
