{
  "id": 358,
  "num": 358,
  "slug": "chimecho",
  "name": "Chimecho",
  "gen": 3,
  "forms": [],
  "isHomeRegistrable": true,
  "isBattleOnly": false,
  "isReversible": false,
  "isGmax": false,
  "formName": null,
  "formSlug": null,
  "formOrder": 0,
  "baseSpecies": null,
  "dataGen": 8,
  "type1": "psychic",
  "type2": null,
  "eggGroup1": "amorphous",
  "eggGroup2": null,
  "ability1": "levitate",
  "ability2": null,
  "abilityHidden": null,
  "height": 60,
  "weight": 100,
  "color": "blue",
  "actualColor": "blue",
  "shape": "head-arms",
  "maleRatio": 0,
  "femaleRatio": 0,
  "growthRate": "fast",
  "catchRate": 45,
  "hatchCycles": 25,
  "baseFriendship": 70,
  "baseStats": {
    "hp": 75,
    "atk": 50,
    "def": 80,
    "spa": 95,
    "spd": 90,
    "spe": 65
  },
  "baseStatsTotal": 455,
  "yieldStats": {
    "hp": 0,
    "atk": 0,
    "def": 0,
    "spa": 1,
    "spd": 1,
    "spe": 0
  },
  "yieldBaseExp": 159,
  "isFemale": false,
  "isCosmetic": false,
  "isLegendary": false,
  "isMythical": false,
  "isFusion": false,
  "isMega": false,
  "isPrimal": false,
  "canDynamax": true,
  "isTotem": false,
  "isAbilityForm": false,
  "isRegional": false,
  "isHomeStorable": true,
  "showdownSlug": "chimecho",
  "veekunSlug": "chimecho",
  "veekunFormId": 358
}
