{
  "id": 896,
  "num": 896,
  "slug": "glastrier",
  "name": "Glastrier",
  "gen": 8,
  "forms": [],
  "formName": null,
  "formSlug": null,
  "formOrder": 0,
  "baseSpecies": null,
  "dataGen": 8,
  "type1": "ice",
  "type2": null,
  "eggGroup1": "undiscovered",
  "eggGroup2": null,
  "ability1": "chilling-neigh",
  "ability2": null,
  "abilityHidden": null,
  "height": 220,
  "weight": 80000,
  "color": "white",
  "actualColor": "white",
  "shape": "quadruped",
  "maleRatio": 0,
  "femaleRatio": 0,
  "growthRate": "slow",
  "catchRate": 3,
  "hatchCycles": 120,
  "baseFriendship": 35,
  "baseStats": {
    "hp": 100,
    "atk": 145,
    "def": 130,
    "spa": 65,
    "spd": 110,
    "spe": 30
  },
  "baseStatsTotal": 580,
  "yieldStats": {
    "hp": 0,
    "atk": 3,
    "def": 0,
    "spa": 0,
    "spd": 0,
    "spe": 0
  },
  "yieldBaseExp": 290,
  "isFemale": false,
  "isCosmetic": false,
  "isLegendary": true,
  "isMythical": false,
  "isFusion": false,
  "isMega": false,
  "isPrimal": false,
  "isGmax": false,
  "canDynamax": true,
  "isTotem": false,
  "isRegional": false,
  "isHomeStorable": true,
  "showdownSlug": "glastrier",
  "veekunSlug": "glastrier",
  "veekunFormId": 896
}
