{
  "id": 10073,
  "num": 105,
  "slug": "marowak-alola",
  "name": "Alolan Marowak",
  "gen": 7,
  "forms": [],
  "isHomeRegistrable": true,
  "isBattleOnly": false,
  "isReversible": false,
  "isGmax": false,
  "formName": "Alolan Form",
  "formSlug": "alola",
  "formOrder": 1,
  "baseSpecies": "marowak",
  "isFemale": false,
  "isCosmetic": false,
  "isLegendary": false,
  "isMythical": false,
  "isFusion": false,
  "isMega": false,
  "isPrimal": false,
  "canDynamax": true,
  "isTotem": false,
  "isAbilityForm": false,
  "isRegional": true,
  "isHomeStorable": true,
  "showdownSlug": "marowakalola",
  "veekunSlug": "marowak-alola",
  "veekunFormId": 10217
}
