{
  "id": 10085,
  "num": 130,
  "slug": "gyarados-f",
  "name": "Gyarados-F",
  "gen": 1,
  "forms": [],
  "formName": "F",
  "formSlug": "f",
  "formOrder": 1,
  "baseSpecies": "gyarados",
  "baseDataForm": "gyarados",
  "imgSprite": "gyarados",
  "imgHome": "0101-0200/0130-f",
  "isFemale": true,
  "isCosmetic": true,
  "isLegendary": false,
  "isMythical": false,
  "isFusion": false,
  "isMega": false,
  "isPrimal": false,
  "isGmax": false,
  "canDynamax": true,
  "isTotem": false,
  "isRegional": false,
  "isHomeStorable": true,
  "showdownSlug": null,
  "veekunSlug": null,
  "veekunFormId": null
}
