{
  "id": 10261,
  "num": 493,
  "slug": "arceus-flying",
  "name": "Arceus (Flying)",
  "gen": 4,
  "forms": [],
  "isHomeRegistrable": true,
  "isBattleOnly": false,
  "isReversible": true,
  "isGmax": false,
  "formName": "Flying",
  "formSlug": "flying",
  "formOrder": 2,
  "baseSpecies": "arceus",
  "isFemale": false,
  "isCosmetic": false,
  "isLegendary": false,
  "isMythical": true,
  "isFusion": false,
  "isMega": false,
  "isPrimal": false,
  "canDynamax": true,
  "isTotem": false,
  "isRegional": false,
  "isHomeStorable": false,
  "showdownSlug": "arceusflying",
  "veekunSlug": "arceus-flying",
  "veekunFormId": 10047
}
