{
  "id": 635,
  "num": 635,
  "slug": "hydreigon",
  "name": "Hydreigon",
  "gen": 5,
  "forms": [],
  "formName": null,
  "formSlug": null,
  "formOrder": 0,
  "baseSpecies": null,
  "baseDataForm": null,
  "imgSprite": "hydreigon",
  "imgHome": "0601-0700/0635",
  "dataGen": 8,
  "type1": "dark",
  "type2": "dragon",
  "eggGroup1": "dragon",
  "eggGroup2": null,
  "ability1": "levitate",
  "ability2": null,
  "abilityHidden": null,
  "height": 180,
  "weight": 16000,
  "color": "blue",
  "actualColor": "blue",
  "shape": "bipedal-tailed",
  "maleRatio": 0,
  "femaleRatio": 0,
  "growthRate": "slow",
  "catchRate": 45,
  "hatchCycles": 40,
  "baseFriendship": 35,
  "baseStats": {
    "hp": 92,
    "atk": 105,
    "def": 90,
    "spa": 125,
    "spd": 90,
    "spe": 98
  },
  "baseStatsTotal": 600,
  "yieldStats": {
    "hp": 0,
    "atk": 0,
    "def": 0,
    "spa": 3,
    "spd": 0,
    "spe": 0
  },
  "yieldBaseExp": 270,
  "isFemale": false,
  "isCosmetic": false,
  "isLegendary": false,
  "isMythical": false,
  "isFusion": false,
  "isMega": false,
  "isPrimal": false,
  "isGmax": false,
  "canDynamax": true,
  "isTotem": false,
  "isRegional": false,
  "isHomeStorable": true,
  "showdownSlug": "hydreigon",
  "veekunSlug": "hydreigon",
  "veekunFormId": 635,
  "title": "Hydreigon"
}