{
  "id": 10322,
  "num": 669,
  "slug": "flabebe-blue",
  "name": "Flabe\u0301be\u0301 Blue Flower",
  "gen": 6,
  "forms": [],
  "isBattleOnly": false,
  "isReversible": false,
  "isGmax": false,
  "formName": "Blue Flower",
  "formSlug": "blue",
  "formOrder": 3,
  "baseSpecies": "flabebe",
  "isFemale": false,
  "isCosmetic": true,
  "isLegendary": false,
  "isMythical": false,
  "isFusion": false,
  "isMega": false,
  "isPrimal": false,
  "canDynamax": true,
  "isTotem": false,
  "isAbilityForm": false,
  "isRegional": false,
  "isHomeStorable": true,
  "isHomeRegistrable": true,
  "showdownSlug": "flabebe",
  "veekunSlug": "flabebe-blue",
  "veekunFormId": 10105
}
