{
  "id": 10389,
  "num": 774,
  "slug": "minior-red",
  "name": "Minior Red Core",
  "gen": 7,
  "forms": [],
  "isHomeRegistrable": true,
  "isBattleOnly": false,
  "isReversible": false,
  "isGmax": false,
  "formName": "Red Core",
  "formSlug": "red",
  "formOrder": 1,
  "baseSpecies": "minior",
  "isFemale": false,
  "isCosmetic": false,
  "isLegendary": false,
  "isMythical": false,
  "isFusion": false,
  "isMega": false,
  "isPrimal": false,
  "canDynamax": true,
  "isTotem": false,
  "isAbilityForm": false,
  "isRegional": false,
  "isHomeStorable": true,
  "showdownSlug": "minior",
  "veekunSlug": "minior-red",
  "veekunFormId": 10255
}
