{
  "id": 476,
  "num": 476,
  "slug": "probopass",
  "name": "Probopass",
  "gen": 4,
  "forms": [],
  "formName": null,
  "formSlug": null,
  "formOrder": 0,
  "baseSpecies": null,
  "baseDataForm": null,
  "imgSprite": "probopass",
  "imgHome": "0401-0500/0476",
  "dataGen": 8,
  "type1": "rock",
  "type2": "steel",
  "eggGroup1": "mineral",
  "eggGroup2": null,
  "ability1": "sturdy",
  "ability2": "magnet-pull",
  "abilityHidden": "sand-force",
  "height": 140,
  "weight": 34000,
  "color": "gray",
  "actualColor": "gray",
  "shape": "multiple",
  "maleRatio": 0,
  "femaleRatio": 0,
  "growthRate": "medium-fast",
  "catchRate": 60,
  "hatchCycles": 20,
  "baseFriendship": 70,
  "baseStats": {
    "hp": 60,
    "atk": 55,
    "def": 145,
    "spa": 75,
    "spd": 150,
    "spe": 40
  },
  "baseStatsTotal": 525,
  "yieldStats": {
    "hp": 0,
    "atk": 0,
    "def": 1,
    "spa": 0,
    "spd": 2,
    "spe": 0
  },
  "yieldBaseExp": 184,
  "isFemale": false,
  "isCosmetic": false,
  "isLegendary": false,
  "isMythical": false,
  "isFusion": false,
  "isMega": false,
  "isPrimal": false,
  "isGmax": false,
  "canDynamax": true,
  "isTotem": false,
  "isRegional": false,
  "isHomeStorable": true,
  "showdownSlug": "probopass",
  "veekunSlug": "probopass",
  "veekunFormId": 476
}
