{
  "id": 10285,
  "num": 586,
  "slug": "sawsbuck-winter",
  "name": "Sawsbuck (Winter)",
  "gen": 5,
  "forms": [],
  "isHomeRegistrable": true,
  "isBattleOnly": false,
  "isReversible": true,
  "isGmax": false,
  "formName": "Winter",
  "formSlug": "winter",
  "formOrder": 3,
  "baseSpecies": "sawsbuck",
  "isFemale": false,
  "isCosmetic": true,
  "isLegendary": false,
  "isMythical": false,
  "isFusion": false,
  "isMega": false,
  "isPrimal": false,
  "canDynamax": true,
  "isTotem": false,
  "isRegional": false,
  "isHomeStorable": true,
  "showdownSlug": "sawsbuck",
  "veekunSlug": "sawsbuck-winter",
  "veekunFormId": 10073
}
