{
  "id": 10465,
  "num": 869,
  "slug": "alcremie-salted-cream-flower",
  "name": "Alcremie (Salted Cream Flower)",
  "gen": 8,
  "forms": [],
  "isBattleOnly": false,
  "isReversible": false,
  "isGmax": false,
  "formName": "Salted Cream Flower",
  "formSlug": "salted-cream-flower",
  "formOrder": 40,
  "baseSpecies": "alcremie",
  "isFemale": false,
  "isCosmetic": true,
  "isLegendary": false,
  "isMythical": false,
  "isFusion": false,
  "isMega": false,
  "isPrimal": false,
  "canDynamax": true,
  "isTotem": false,
  "isAbilityForm": false,
  "isRegional": false,
  "isHomeStorable": true,
  "isHomeRegistrable": true,
  "showdownSlug": "alcremie",
  "veekunSlug": "alcremie-salted-cream",
  "veekunFormId": 10350
}
