{
  "id": 10501,
  "num": 898,
  "slug": "calyrex-ice",
  "name": "Calyrex (Ice)",
  "gen": 8,
  "forms": [],
  "isHomeRegistrable": true,
  "isBattleOnly": false,
  "isReversible": true,
  "isGmax": false,
  "formName": "Ice",
  "formSlug": "ice",
  "formOrder": 1,
  "baseSpecies": "calyrex",
  "isFemale": false,
  "isCosmetic": false,
  "isLegendary": true,
  "isMythical": false,
  "isFusion": true,
  "isMega": false,
  "isPrimal": false,
  "canDynamax": true,
  "isTotem": false,
  "isRegional": false,
  "isHomeStorable": false,
  "showdownSlug": "calyrexice",
  "veekunSlug": "calyrex-ice",
  "veekunFormId": 10362
}
