{
  "id": 886,
  "num": 886,
  "slug": "drakloak",
  "name": "Drakloak",
  "gen": 8,
  "forms": [],
  "formName": null,
  "formSlug": null,
  "formOrder": 0,
  "baseSpecies": null,
  "baseDataForm": null,
  "imgSprite": "drakloak",
  "imgHome": "0801-0900/0886",
  "dataGen": 8,
  "type1": "dragon",
  "type2": "ghost",
  "eggGroup1": "amorphous",
  "eggGroup2": "dragon",
  "ability1": "clear-body",
  "ability2": "infiltrator",
  "abilityHidden": "cursed-body",
  "height": 140,
  "weight": 1100,
  "color": "green",
  "actualColor": "green",
  "shape": "head-arms",
  "maleRatio": 0,
  "femaleRatio": 0,
  "growthRate": "slow",
  "catchRate": -1,
  "hatchCycles": -1,
  "baseFriendship": -1,
  "baseStats": {
    "hp": 68,
    "atk": 80,
    "def": 50,
    "spa": 60,
    "spd": 50,
    "spe": 102
  },
  "baseStatsTotal": 410,
  "yieldStats": {
    "hp": -1,
    "atk": -1,
    "def": -1,
    "spa": -1,
    "spd": -1,
    "spe": -1
  },
  "yieldBaseExp": -1,
  "isFemale": false,
  "isCosmetic": false,
  "isLegendary": false,
  "isMythical": false,
  "isFusion": false,
  "isMega": false,
  "isPrimal": false,
  "isGmax": false,
  "canDynamax": true,
  "isTotem": false,
  "isRegional": false,
  "isHomeStorable": true,
  "showdownSlug": "drakloak",
  "veekunSlug": null,
  "veekunFormId": null,
  "title": "Drakloak"
}