{
  "id": 130,
  "num": 130,
  "slug": "gyarados",
  "name": "Gyarados",
  "gen": 1,
  "forms": [
    "gyarados-f",
    "gyarados-mega"
  ],
  "formName": null,
  "formSlug": null,
  "formOrder": 0,
  "baseSpecies": null,
  "baseDataForm": null,
  "imgSprite": "gyarados",
  "imgHome": "0101-0200/0130",
  "dataGen": 8,
  "type1": "water",
  "type2": "flying",
  "eggGroup1": "water-2",
  "eggGroup2": "dragon",
  "ability1": "intimidate",
  "ability2": null,
  "abilityHidden": "moxie",
  "height": 650,
  "weight": 23500,
  "color": "blue",
  "actualColor": "blue",
  "shape": "serpentine",
  "maleRatio": 0,
  "femaleRatio": 0,
  "growthRate": "slow",
  "catchRate": 45,
  "hatchCycles": 5,
  "baseFriendship": 70,
  "baseStats": {
    "hp": 95,
    "atk": 125,
    "def": 79,
    "spa": 60,
    "spd": 100,
    "spe": 81
  },
  "baseStatsTotal": 540,
  "yieldStats": {
    "hp": 0,
    "atk": 2,
    "def": 0,
    "spa": 0,
    "spd": 0,
    "spe": 0
  },
  "yieldBaseExp": 189,
  "isFemale": false,
  "isCosmetic": false,
  "isLegendary": false,
  "isMythical": false,
  "isFusion": false,
  "isMega": false,
  "isPrimal": false,
  "isGmax": false,
  "canDynamax": true,
  "isTotem": false,
  "isRegional": false,
  "isHomeStorable": true,
  "showdownSlug": "gyarados",
  "veekunSlug": "gyarados",
  "veekunFormId": 130,
  "title": "Gyarados"
}