{
  "id": 10360,
  "num": 738,
  "slug": "vikavolt-totem",
  "name": "Vikavolt (Totem)",
  "gen": 7,
  "forms": [],
  "isHomeRegistrable": false,
  "isBattleOnly": false,
  "isReversible": false,
  "isGmax": false,
  "formName": "Totem",
  "formSlug": "totem",
  "formOrder": 1,
  "baseSpecies": "vikavolt",
  "isFemale": false,
  "isCosmetic": false,
  "isLegendary": false,
  "isMythical": false,
  "isFusion": false,
  "isMega": false,
  "isPrimal": false,
  "canDynamax": true,
  "isTotem": true,
  "isRegional": false,
  "isHomeStorable": false,
  "showdownSlug": "vikavolttotem",
  "veekunSlug": "vikavolt-totem",
  "veekunFormId": 10224
}
