{
  "id": 293,
  "num": 293,
  "slug": "whismur",
  "name": "Whismur",
  "gen": 3,
  "forms": [],
  "formName": null,
  "formSlug": null,
  "formOrder": 0,
  "baseSpecies": null,
  "baseDataForm": null,
  "imgSprite": "whismur",
  "imgHome": "0293",
  "dataGen": 8,
  "type1": "normal",
  "type2": null,
  "eggGroup1": "monster",
  "eggGroup2": "field",
  "ability1": "soundproof",
  "ability2": null,
  "abilityHidden": "rattled",
  "height": 60,
  "weight": 1630,
  "color": "pink",
  "actualColor": "pink",
  "shape": "bipedal-tailed",
  "maleRatio": 0,
  "femaleRatio": 0,
  "growthRate": "medium-slow",
  "catchRate": 190,
  "hatchCycles": 20,
  "baseFriendship": 50,
  "baseStats": {
    "hp": 64,
    "atk": 51,
    "def": 23,
    "spa": 51,
    "spd": 23,
    "spe": 28
  },
  "baseStatsTotal": 240,
  "yieldStats": {
    "hp": 1,
    "atk": 0,
    "def": 0,
    "spa": 0,
    "spd": 0,
    "spe": 0
  },
  "yieldBaseExp": 48,
  "isFemale": false,
  "isCosmetic": false,
  "isLegendary": false,
  "isMythical": false,
  "isFusion": false,
  "isMega": false,
  "isPrimal": false,
  "isGmax": false,
  "canDynamax": true,
  "isTotem": false,
  "isRegional": false,
  "isHomeStorable": true,
  "showdownSlug": "whismur",
  "veekunSlug": "whismur",
  "veekunFormId": 293
}
