{
  "id": 408,
  "num": 408,
  "slug": "cranidos",
  "name": "Cranidos",
  "gen": 4,
  "forms": [],
  "formName": null,
  "formSlug": null,
  "formOrder": 0,
  "baseSpecies": null,
  "baseDataForm": null,
  "imgSprite": "cranidos",
  "imgHome": "0401-0500/0408",
  "dataGen": 8,
  "type1": "rock",
  "type2": null,
  "eggGroup1": "monster",
  "eggGroup2": null,
  "ability1": "mold-breaker",
  "ability2": null,
  "abilityHidden": "sheer-force",
  "height": 90,
  "weight": 3150,
  "color": "blue",
  "actualColor": "blue",
  "shape": "bipedal-tailed",
  "maleRatio": 0,
  "femaleRatio": 0,
  "growthRate": "erratic",
  "catchRate": 45,
  "hatchCycles": 30,
  "baseFriendship": 70,
  "baseStats": {
    "hp": 67,
    "atk": 125,
    "def": 40,
    "spa": 30,
    "spd": 30,
    "spe": 58
  },
  "baseStatsTotal": 350,
  "yieldStats": {
    "hp": 0,
    "atk": 1,
    "def": 0,
    "spa": 0,
    "spd": 0,
    "spe": 0
  },
  "yieldBaseExp": 70,
  "isFemale": false,
  "isCosmetic": false,
  "isLegendary": false,
  "isMythical": false,
  "isFusion": false,
  "isMega": false,
  "isPrimal": false,
  "isGmax": false,
  "canDynamax": true,
  "isTotem": false,
  "isRegional": false,
  "isHomeStorable": true,
  "showdownSlug": "cranidos",
  "veekunSlug": "cranidos",
  "veekunFormId": 408
}
