[
  {
    "id": 1,
    "slug": "stench",
    "name": "Stench",
    "gen": 3,
    "rating": 10,
    "showdownName": "Stench",
    "veekunName": "stench"
  },
  {
    "id": 2,
    "slug": "drizzle",
    "name": "Drizzle",
    "gen": 3,
    "rating": 80,
    "showdownName": "Drizzle",
    "veekunName": "drizzle"
  },
  {
    "id": 3,
    "slug": "speed-boost",
    "name": "Speed Boost",
    "gen": 3,
    "rating": 90,
    "showdownName": "Speed Boost",
    "veekunName": "speed-boost"
  },
  {
    "id": 4,
    "slug": "battle-armor",
    "name": "Battle Armor",
    "gen": 3,
    "rating": 20,
    "showdownName": "Battle Armor",
    "veekunName": "battle-armor"
  },
  {
    "id": 5,
    "slug": "sturdy",
    "name": "Sturdy",
    "gen": 3,
    "rating": 60,
    "showdownName": "Sturdy",
    "veekunName": "sturdy"
  },
  {
    "id": 6,
    "slug": "damp",
    "name": "Damp",
    "gen": 3,
    "rating": 20,
    "showdownName": "Damp",
    "veekunName": "damp"
  },
  {
    "id": 7,
    "slug": "limber",
    "name": "Limber",
    "gen": 3,
    "rating": 40,
    "showdownName": "Limber",
    "veekunName": "limber"
  },
  {
    "id": 8,
    "slug": "sand-veil",
    "name": "Sand Veil",
    "gen": 3,
    "rating": 30,
    "showdownName": "Sand Veil",
    "veekunName": "sand-veil"
  },
  {
    "id": 9,
    "slug": "static",
    "name": "Static",
    "gen": 3,
    "rating": 40,
    "showdownName": "Static",
    "veekunName": "static"
  },
  {
    "id": 10,
    "slug": "volt-absorb",
    "name": "Volt Absorb",
    "gen": 3,
    "rating": 70,
    "showdownName": "Volt Absorb",
    "veekunName": "volt-absorb"
  },
  {
    "id": 11,
    "slug": "water-absorb",
    "name": "Water Absorb",
    "gen": 3,
    "rating": 70,
    "showdownName": "Water Absorb",
    "veekunName": "water-absorb"
  },
  {
    "id": 12,
    "slug": "oblivious",
    "name": "Oblivious",
    "gen": 3,
    "rating": 30,
    "showdownName": "Oblivious",
    "veekunName": "oblivious"
  },
  {
    "id": 13,
    "slug": "cloud-nine",
    "name": "Cloud Nine",
    "gen": 3,
    "rating": 40,
    "showdownName": "Cloud Nine",
    "veekunName": "cloud-nine"
  },
  {
    "id": 14,
    "slug": "compound-eyes",
    "name": "Compound Eyes",
    "gen": 3,
    "rating": 60,
    "showdownName": "Compound Eyes",
    "veekunName": "compound-eyes"
  },
  {
    "id": 15,
    "slug": "insomnia",
    "name": "Insomnia",
    "gen": 3,
    "rating": 40,
    "showdownName": "Insomnia",
    "veekunName": "insomnia"
  },
  {
    "id": 16,
    "slug": "color-change",
    "name": "Color Change",
    "gen": 3,
    "rating": 0,
    "showdownName": "Color Change",
    "veekunName": "color-change"
  },
  {
    "id": 17,
    "slug": "immunity",
    "name": "Immunity",
    "gen": 3,
    "rating": 40,
    "showdownName": "Immunity",
    "veekunName": "immunity"
  },
  {
    "id": 18,
    "slug": "flash-fire",
    "name": "Flash Fire",
    "gen": 3,
    "rating": 70,
    "showdownName": "Flash Fire",
    "veekunName": "flash-fire"
  },
  {
    "id": 19,
    "slug": "shield-dust",
    "name": "Shield Dust",
    "gen": 3,
    "rating": 40,
    "showdownName": "Shield Dust",
    "veekunName": "shield-dust"
  },
  {
    "id": 20,
    "slug": "own-tempo",
    "name": "Own Tempo",
    "gen": 3,
    "rating": 30,
    "showdownName": "Own Tempo",
    "veekunName": "own-tempo"
  },
  {
    "id": 21,
    "slug": "suction-cups",
    "name": "Suction Cups",
    "gen": 3,
    "rating": 20,
    "showdownName": "Suction Cups",
    "veekunName": "suction-cups"
  },
  {
    "id": 22,
    "slug": "intimidate",
    "name": "Intimidate",
    "gen": 3,
    "rating": 70,
    "showdownName": "Intimidate",
    "veekunName": "intimidate"
  },
  {
    "id": 23,
    "slug": "shadow-tag",
    "name": "Shadow Tag",
    "gen": 3,
    "rating": 100,
    "showdownName": "Shadow Tag",
    "veekunName": "shadow-tag"
  },
  {
    "id": 24,
    "slug": "rough-skin",
    "name": "Rough Skin",
    "gen": 3,
    "rating": 50,
    "showdownName": "Rough Skin",
    "veekunName": "rough-skin"
  },
  {
    "id": 25,
    "slug": "wonder-guard",
    "name": "Wonder Guard",
    "gen": 3,
    "rating": 100,
    "showdownName": "Wonder Guard",
    "veekunName": "wonder-guard"
  },
  {
    "id": 26,
    "slug": "levitate",
    "name": "Levitate",
    "gen": 3,
    "rating": 70,
    "showdownName": "Levitate",
    "veekunName": "levitate"
  },
  {
    "id": 27,
    "slug": "effect-spore",
    "name": "Effect Spore",
    "gen": 3,
    "rating": 40,
    "showdownName": "Effect Spore",
    "veekunName": "effect-spore"
  },
  {
    "id": 28,
    "slug": "synchronize",
    "name": "Synchronize",
    "gen": 3,
    "rating": 40,
    "showdownName": "Synchronize",
    "veekunName": "synchronize"
  },
  {
    "id": 29,
    "slug": "clear-body",
    "name": "Clear Body",
    "gen": 3,
    "rating": 40,
    "showdownName": "Clear Body",
    "veekunName": "clear-body"
  },
  {
    "id": 30,
    "slug": "natural-cure",
    "name": "Natural Cure",
    "gen": 3,
    "rating": 50,
    "showdownName": "Natural Cure",
    "veekunName": "natural-cure"
  },
  {
    "id": 31,
    "slug": "lightning-rod",
    "name": "Lightning Rod",
    "gen": 3,
    "rating": 60,
    "showdownName": "Lightning Rod",
    "veekunName": "lightning-rod"
  },
  {
    "id": 32,
    "slug": "serene-grace",
    "name": "Serene Grace",
    "gen": 3,
    "rating": 70,
    "showdownName": "Serene Grace",
    "veekunName": "serene-grace"
  },
  {
    "id": 33,
    "slug": "swift-swim",
    "name": "Swift Swim",
    "gen": 3,
    "rating": 60,
    "showdownName": "Swift Swim",
    "veekunName": "swift-swim"
  },
  {
    "id": 34,
    "slug": "chlorophyll",
    "name": "Chlorophyll",
    "gen": 3,
    "rating": 60,
    "showdownName": "Chlorophyll",
    "veekunName": "chlorophyll"
  },
  {
    "id": 35,
    "slug": "illuminate",
    "name": "Illuminate",
    "gen": 3,
    "rating": 0,
    "showdownName": "Illuminate",
    "veekunName": "illuminate"
  },
  {
    "id": 36,
    "slug": "trace",
    "name": "Trace",
    "gen": 3,
    "rating": 50,
    "showdownName": "Trace",
    "veekunName": "trace"
  },
  {
    "id": 37,
    "slug": "huge-power",
    "name": "Huge Power",
    "gen": 3,
    "rating": 100,
    "showdownName": "Huge Power",
    "veekunName": "huge-power"
  },
  {
    "id": 38,
    "slug": "poison-point",
    "name": "Poison Point",
    "gen": 3,
    "rating": 30,
    "showdownName": "Poison Point",
    "veekunName": "poison-point"
  },
  {
    "id": 39,
    "slug": "inner-focus",
    "name": "Inner Focus",
    "gen": 3,
    "rating": 30,
    "showdownName": "Inner Focus",
    "veekunName": "inner-focus"
  },
  {
    "id": 40,
    "slug": "magma-armor",
    "name": "Magma Armor",
    "gen": 3,
    "rating": 20,
    "showdownName": "Magma Armor",
    "veekunName": "magma-armor"
  },
  {
    "id": 41,
    "slug": "water-veil",
    "name": "Water Veil",
    "gen": 3,
    "rating": 40,
    "showdownName": "Water Veil",
    "veekunName": "water-veil"
  },
  {
    "id": 42,
    "slug": "magnet-pull",
    "name": "Magnet Pull",
    "gen": 3,
    "rating": 80,
    "showdownName": "Magnet Pull",
    "veekunName": "magnet-pull"
  },
  {
    "id": 43,
    "slug": "soundproof",
    "name": "Soundproof",
    "gen": 3,
    "rating": 30,
    "showdownName": "Soundproof",
    "veekunName": "soundproof"
  },
  {
    "id": 44,
    "slug": "rain-dish",
    "name": "Rain Dish",
    "gen": 3,
    "rating": 30,
    "showdownName": "Rain Dish",
    "veekunName": "rain-dish"
  },
  {
    "id": 45,
    "slug": "sand-stream",
    "name": "Sand Stream",
    "gen": 3,
    "rating": 80,
    "showdownName": "Sand Stream",
    "veekunName": "sand-stream"
  },
  {
    "id": 46,
    "slug": "pressure",
    "name": "Pressure",
    "gen": 3,
    "rating": 50,
    "showdownName": "Pressure",
    "veekunName": "pressure"
  },
  {
    "id": 47,
    "slug": "thick-fat",
    "name": "Thick Fat",
    "gen": 3,
    "rating": 70,
    "showdownName": "Thick Fat",
    "veekunName": "thick-fat"
  },
  {
    "id": 48,
    "slug": "early-bird",
    "name": "Early Bird",
    "gen": 3,
    "rating": 30,
    "showdownName": "Early Bird",
    "veekunName": "early-bird"
  },
  {
    "id": 49,
    "slug": "flame-body",
    "name": "Flame Body",
    "gen": 3,
    "rating": 40,
    "showdownName": "Flame Body",
    "veekunName": "flame-body"
  },
  {
    "id": 50,
    "slug": "run-away",
    "name": "Run Away",
    "gen": 3,
    "rating": 0,
    "showdownName": "Run Away",
    "veekunName": "run-away"
  },
  {
    "id": 51,
    "slug": "keen-eye",
    "name": "Keen Eye",
    "gen": 3,
    "rating": 10,
    "showdownName": "Keen Eye",
    "veekunName": "keen-eye"
  },
  {
    "id": 52,
    "slug": "hyper-cutter",
    "name": "Hyper Cutter",
    "gen": 3,
    "rating": 30,
    "showdownName": "Hyper Cutter",
    "veekunName": "hyper-cutter"
  },
  {
    "id": 53,
    "slug": "pickup",
    "name": "Pickup",
    "gen": 3,
    "rating": 10,
    "showdownName": "Pickup",
    "veekunName": "pickup"
  },
  {
    "id": 54,
    "slug": "truant",
    "name": "Truant",
    "gen": 3,
    "rating": -20,
    "showdownName": "Truant",
    "veekunName": "truant"
  },
  {
    "id": 55,
    "slug": "hustle",
    "name": "Hustle",
    "gen": 3,
    "rating": 70,
    "showdownName": "Hustle",
    "veekunName": "hustle"
  },
  {
    "id": 56,
    "slug": "cute-charm",
    "name": "Cute Charm",
    "gen": 3,
    "rating": 10,
    "showdownName": "Cute Charm",
    "veekunName": "cute-charm"
  },
  {
    "id": 57,
    "slug": "plus",
    "name": "Plus",
    "gen": 3,
    "rating": 0,
    "showdownName": "Plus",
    "veekunName": "plus"
  },
  {
    "id": 58,
    "slug": "minus",
    "name": "Minus",
    "gen": 3,
    "rating": 0,
    "showdownName": "Minus",
    "veekunName": "minus"
  },
  {
    "id": 59,
    "slug": "forecast",
    "name": "Forecast",
    "gen": 3,
    "rating": 40,
    "showdownName": "Forecast",
    "veekunName": "forecast"
  },
  {
    "id": 60,
    "slug": "sticky-hold",
    "name": "Sticky Hold",
    "gen": 3,
    "rating": 40,
    "showdownName": "Sticky Hold",
    "veekunName": "sticky-hold"
  },
  {
    "id": 61,
    "slug": "shed-skin",
    "name": "Shed Skin",
    "gen": 3,
    "rating": 60,
    "showdownName": "Shed Skin",
    "veekunName": "shed-skin"
  },
  {
    "id": 62,
    "slug": "guts",
    "name": "Guts",
    "gen": 3,
    "rating": 60,
    "showdownName": "Guts",
    "veekunName": "guts"
  },
  {
    "id": 63,
    "slug": "marvel-scale",
    "name": "Marvel Scale",
    "gen": 3,
    "rating": 50,
    "showdownName": "Marvel Scale",
    "veekunName": "marvel-scale"
  },
  {
    "id": 64,
    "slug": "liquid-ooze",
    "name": "Liquid Ooze",
    "gen": 3,
    "rating": 30,
    "showdownName": "Liquid Ooze",
    "veekunName": "liquid-ooze"
  },
  {
    "id": 65,
    "slug": "overgrow",
    "name": "Overgrow",
    "gen": 3,
    "rating": 40,
    "showdownName": "Overgrow",
    "veekunName": "overgrow"
  },
  {
    "id": 66,
    "slug": "blaze",
    "name": "Blaze",
    "gen": 3,
    "rating": 40,
    "showdownName": "Blaze",
    "veekunName": "blaze"
  },
  {
    "id": 67,
    "slug": "torrent",
    "name": "Torrent",
    "gen": 3,
    "rating": 40,
    "showdownName": "Torrent",
    "veekunName": "torrent"
  },
  {
    "id": 68,
    "slug": "swarm",
    "name": "Swarm",
    "gen": 3,
    "rating": 40,
    "showdownName": "Swarm",
    "veekunName": "swarm"
  },
  {
    "id": 69,
    "slug": "rock-head",
    "name": "Rock Head",
    "gen": 3,
    "rating": 60,
    "showdownName": "Rock Head",
    "veekunName": "rock-head"
  },
  {
    "id": 70,
    "slug": "drought",
    "name": "Drought",
    "gen": 3,
    "rating": 80,
    "showdownName": "Drought",
    "veekunName": "drought"
  },
  {
    "id": 71,
    "slug": "arena-trap",
    "name": "Arena Trap",
    "gen": 3,
    "rating": 100,
    "showdownName": "Arena Trap",
    "veekunName": "arena-trap"
  },
  {
    "id": 72,
    "slug": "vital-spirit",
    "name": "Vital Spirit",
    "gen": 3,
    "rating": 40,
    "showdownName": "Vital Spirit",
    "veekunName": "vital-spirit"
  },
  {
    "id": 73,
    "slug": "white-smoke",
    "name": "White Smoke",
    "gen": 3,
    "rating": 40,
    "showdownName": "White Smoke",
    "veekunName": "white-smoke"
  },
  {
    "id": 74,
    "slug": "pure-power",
    "name": "Pure Power",
    "gen": 3,
    "rating": 100,
    "showdownName": "Pure Power",
    "veekunName": "pure-power"
  },
  {
    "id": 75,
    "slug": "shell-armor",
    "name": "Shell Armor",
    "gen": 3,
    "rating": 20,
    "showdownName": "Shell Armor",
    "veekunName": "shell-armor"
  },
  {
    "id": 76,
    "slug": "air-lock",
    "name": "Air Lock",
    "gen": 3,
    "rating": 40,
    "showdownName": "Air Lock",
    "veekunName": "air-lock"
  },
  {
    "id": 77,
    "slug": "tangled-feet",
    "name": "Tangled Feet",
    "gen": 4,
    "rating": 20,
    "showdownName": "Tangled Feet",
    "veekunName": "tangled-feet"
  },
  {
    "id": 78,
    "slug": "motor-drive",
    "name": "Motor Drive",
    "gen": 4,
    "rating": 60,
    "showdownName": "Motor Drive",
    "veekunName": "motor-drive"
  },
  {
    "id": 79,
    "slug": "rivalry",
    "name": "Rivalry",
    "gen": 4,
    "rating": 0,
    "showdownName": "Rivalry",
    "veekunName": "rivalry"
  },
  {
    "id": 80,
    "slug": "steadfast",
    "name": "Steadfast",
    "gen": 4,
    "rating": 20,
    "showdownName": "Steadfast",
    "veekunName": "steadfast"
  },
  {
    "id": 81,
    "slug": "snow-cloak",
    "name": "Snow Cloak",
    "gen": 4,
    "rating": 30,
    "showdownName": "Snow Cloak",
    "veekunName": "snow-cloak"
  },
  {
    "id": 82,
    "slug": "gluttony",
    "name": "Gluttony",
    "gen": 4,
    "rating": 30,
    "showdownName": "Gluttony",
    "veekunName": "gluttony"
  },
  {
    "id": 83,
    "slug": "anger-point",
    "name": "Anger Point",
    "gen": 4,
    "rating": 30,
    "showdownName": "Anger Point",
    "veekunName": "anger-point"
  },
  {
    "id": 84,
    "slug": "unburden",
    "name": "Unburden",
    "gen": 4,
    "rating": 70,
    "showdownName": "Unburden",
    "veekunName": "unburden"
  },
  {
    "id": 85,
    "slug": "heatproof",
    "name": "Heatproof",
    "gen": 4,
    "rating": 40,
    "showdownName": "Heatproof",
    "veekunName": "heatproof"
  },
  {
    "id": 86,
    "slug": "simple",
    "name": "Simple",
    "gen": 4,
    "rating": 80,
    "showdownName": "Simple",
    "veekunName": "simple"
  },
  {
    "id": 87,
    "slug": "dry-skin",
    "name": "Dry Skin",
    "gen": 4,
    "rating": 60,
    "showdownName": "Dry Skin",
    "veekunName": "dry-skin"
  },
  {
    "id": 88,
    "slug": "download",
    "name": "Download",
    "gen": 4,
    "rating": 70,
    "showdownName": "Download",
    "veekunName": "download"
  },
  {
    "id": 89,
    "slug": "iron-fist",
    "name": "Iron Fist",
    "gen": 4,
    "rating": 60,
    "showdownName": "Iron Fist",
    "veekunName": "iron-fist"
  },
  {
    "id": 90,
    "slug": "poison-heal",
    "name": "Poison Heal",
    "gen": 4,
    "rating": 80,
    "showdownName": "Poison Heal",
    "veekunName": "poison-heal"
  },
  {
    "id": 91,
    "slug": "adaptability",
    "name": "Adaptability",
    "gen": 4,
    "rating": 80,
    "showdownName": "Adaptability",
    "veekunName": "adaptability"
  },
  {
    "id": 92,
    "slug": "skill-link",
    "name": "Skill Link",
    "gen": 4,
    "rating": 60,
    "showdownName": "Skill Link",
    "veekunName": "skill-link"
  },
  {
    "id": 93,
    "slug": "hydration",
    "name": "Hydration",
    "gen": 4,
    "rating": 30,
    "showdownName": "Hydration",
    "veekunName": "hydration"
  },
  {
    "id": 94,
    "slug": "solar-power",
    "name": "Solar Power",
    "gen": 4,
    "rating": 40,
    "showdownName": "Solar Power",
    "veekunName": "solar-power"
  },
  {
    "id": 95,
    "slug": "quick-feet",
    "name": "Quick Feet",
    "gen": 4,
    "rating": 50,
    "showdownName": "Quick Feet",
    "veekunName": "quick-feet"
  },
  {
    "id": 96,
    "slug": "normalize",
    "name": "Normalize",
    "gen": 4,
    "rating": 0,
    "showdownName": "Normalize",
    "veekunName": "normalize"
  },
  {
    "id": 97,
    "slug": "sniper",
    "name": "Sniper",
    "gen": 4,
    "rating": 40,
    "showdownName": "Sniper",
    "veekunName": "sniper"
  },
  {
    "id": 98,
    "slug": "magic-guard",
    "name": "Magic Guard",
    "gen": 4,
    "rating": 80,
    "showdownName": "Magic Guard",
    "veekunName": "magic-guard"
  },
  {
    "id": 99,
    "slug": "no-guard",
    "name": "No Guard",
    "gen": 4,
    "rating": 80,
    "showdownName": "No Guard",
    "veekunName": "no-guard"
  },
  {
    "id": 100,
    "slug": "stall",
    "name": "Stall",
    "gen": 4,
    "rating": -20,
    "showdownName": "Stall",
    "veekunName": "stall"
  },
  {
    "id": 101,
    "slug": "technician",
    "name": "Technician",
    "gen": 4,
    "rating": 70,
    "showdownName": "Technician",
    "veekunName": "technician"
  },
  {
    "id": 102,
    "slug": "leaf-guard",
    "name": "Leaf Guard",
    "gen": 4,
    "rating": 10,
    "showdownName": "Leaf Guard",
    "veekunName": "leaf-guard"
  },
  {
    "id": 103,
    "slug": "klutz",
    "name": "Klutz",
    "gen": 4,
    "rating": -20,
    "showdownName": "Klutz",
    "veekunName": "klutz"
  },
  {
    "id": 104,
    "slug": "mold-breaker",
    "name": "Mold Breaker",
    "gen": 4,
    "rating": 70,
    "showdownName": "Mold Breaker",
    "veekunName": "mold-breaker"
  },
  {
    "id": 105,
    "slug": "super-luck",
    "name": "Super Luck",
    "gen": 4,
    "rating": 30,
    "showdownName": "Super Luck",
    "veekunName": "super-luck"
  },
  {
    "id": 106,
    "slug": "aftermath",
    "name": "Aftermath",
    "gen": 4,
    "rating": 50,
    "showdownName": "Aftermath",
    "veekunName": "aftermath"
  },
  {
    "id": 107,
    "slug": "anticipation",
    "name": "Anticipation",
    "gen": 4,
    "rating": 10,
    "showdownName": "Anticipation",
    "veekunName": "anticipation"
  },
  {
    "id": 108,
    "slug": "forewarn",
    "name": "Forewarn",
    "gen": 4,
    "rating": 10,
    "showdownName": "Forewarn",
    "veekunName": "forewarn"
  },
  {
    "id": 109,
    "slug": "unaware",
    "name": "Unaware",
    "gen": 4,
    "rating": 80,
    "showdownName": "Unaware",
    "veekunName": "unaware"
  },
  {
    "id": 110,
    "slug": "tinted-lens",
    "name": "Tinted Lens",
    "gen": 4,
    "rating": 80,
    "showdownName": "Tinted Lens",
    "veekunName": "tinted-lens"
  },
  {
    "id": 111,
    "slug": "filter",
    "name": "Filter",
    "gen": 4,
    "rating": 60,
    "showdownName": "Filter",
    "veekunName": "filter"
  },
  {
    "id": 112,
    "slug": "slow-start",
    "name": "Slow Start",
    "gen": 4,
    "rating": -20,
    "showdownName": "Slow Start",
    "veekunName": "slow-start"
  },
  {
    "id": 113,
    "slug": "scrappy",
    "name": "Scrappy",
    "gen": 4,
    "rating": 60,
    "showdownName": "Scrappy",
    "veekunName": "scrappy"
  },
  {
    "id": 114,
    "slug": "storm-drain",
    "name": "Storm Drain",
    "gen": 4,
    "rating": 60,
    "showdownName": "Storm Drain",
    "veekunName": "storm-drain"
  },
  {
    "id": 115,
    "slug": "ice-body",
    "name": "Ice Body",
    "gen": 4,
    "rating": 20,
    "showdownName": "Ice Body",
    "veekunName": "ice-body"
  },
  {
    "id": 116,
    "slug": "solid-rock",
    "name": "Solid Rock",
    "gen": 4,
    "rating": 60,
    "showdownName": "Solid Rock",
    "veekunName": "solid-rock"
  },
  {
    "id": 117,
    "slug": "snow-warning",
    "name": "Snow Warning",
    "gen": 4,
    "rating": 80,
    "showdownName": "Snow Warning",
    "veekunName": "snow-warning"
  },
  {
    "id": 118,
    "slug": "honey-gather",
    "name": "Honey Gather",
    "gen": 4,
    "rating": 0,
    "showdownName": "Honey Gather",
    "veekunName": "honey-gather"
  },
  {
    "id": 119,
    "slug": "frisk",
    "name": "Frisk",
    "gen": 4,
    "rating": 30,
    "showdownName": "Frisk",
    "veekunName": "frisk"
  },
  {
    "id": 120,
    "slug": "reckless",
    "name": "Reckless",
    "gen": 4,
    "rating": 60,
    "showdownName": "Reckless",
    "veekunName": "reckless"
  },
  {
    "id": 121,
    "slug": "multitype",
    "name": "Multitype",
    "gen": 4,
    "rating": 80,
    "showdownName": "Multitype",
    "veekunName": "multitype"
  },
  {
    "id": 122,
    "slug": "flower-gift",
    "name": "Flower Gift",
    "gen": 4,
    "rating": 20,
    "showdownName": "Flower Gift",
    "veekunName": "flower-gift"
  },
  {
    "id": 123,
    "slug": "bad-dreams",
    "name": "Bad Dreams",
    "gen": 4,
    "rating": 30,
    "showdownName": "Bad Dreams",
    "veekunName": "bad-dreams"
  },
  {
    "id": 124,
    "slug": "pickpocket",
    "name": "Pickpocket",
    "gen": 5,
    "rating": 20,
    "showdownName": "Pickpocket",
    "veekunName": "pickpocket"
  },
  {
    "id": 125,
    "slug": "sheer-force",
    "name": "Sheer Force",
    "gen": 5,
    "rating": 70,
    "showdownName": "Sheer Force",
    "veekunName": "sheer-force"
  },
  {
    "id": 126,
    "slug": "contrary",
    "name": "Contrary",
    "gen": 5,
    "rating": 90,
    "showdownName": "Contrary",
    "veekunName": "contrary"
  },
  {
    "id": 127,
    "slug": "unnerve",
    "name": "Unnerve",
    "gen": 5,
    "rating": 30,
    "showdownName": "Unnerve",
    "veekunName": "unnerve"
  },
  {
    "id": 128,
    "slug": "defiant",
    "name": "Defiant",
    "gen": 5,
    "rating": 50,
    "showdownName": "Defiant",
    "veekunName": "defiant"
  },
  {
    "id": 129,
    "slug": "defeatist",
    "name": "Defeatist",
    "gen": 5,
    "rating": -20,
    "showdownName": "Defeatist",
    "veekunName": "defeatist"
  },
  {
    "id": 130,
    "slug": "cursed-body",
    "name": "Cursed Body",
    "gen": 5,
    "rating": 40,
    "showdownName": "Cursed Body",
    "veekunName": "cursed-body"
  },
  {
    "id": 131,
    "slug": "healer",
    "name": "Healer",
    "gen": 5,
    "rating": 0,
    "showdownName": "Healer",
    "veekunName": "healer"
  },
  {
    "id": 132,
    "slug": "friend-guard",
    "name": "Friend Guard",
    "gen": 5,
    "rating": 0,
    "showdownName": "Friend Guard",
    "veekunName": "friend-guard"
  },
  {
    "id": 133,
    "slug": "weak-armor",
    "name": "Weak Armor",
    "gen": 5,
    "rating": 20,
    "showdownName": "Weak Armor",
    "veekunName": "weak-armor"
  },
  {
    "id": 134,
    "slug": "heavy-metal",
    "name": "Heavy Metal",
    "gen": 5,
    "rating": 0,
    "showdownName": "Heavy Metal",
    "veekunName": "heavy-metal"
  },
  {
    "id": 135,
    "slug": "light-metal",
    "name": "Light Metal",
    "gen": 5,
    "rating": 20,
    "showdownName": "Light Metal",
    "veekunName": "light-metal"
  },
  {
    "id": 136,
    "slug": "multiscale",
    "name": "Multiscale",
    "gen": 5,
    "rating": 70,
    "showdownName": "Multiscale",
    "veekunName": "multiscale"
  },
  {
    "id": 137,
    "slug": "toxic-boost",
    "name": "Toxic Boost",
    "gen": 5,
    "rating": 50,
    "showdownName": "Toxic Boost",
    "veekunName": "toxic-boost"
  },
  {
    "id": 138,
    "slug": "flare-boost",
    "name": "Flare Boost",
    "gen": 5,
    "rating": 40,
    "showdownName": "Flare Boost",
    "veekunName": "flare-boost"
  },
  {
    "id": 139,
    "slug": "harvest",
    "name": "Harvest",
    "gen": 5,
    "rating": 50,
    "showdownName": "Harvest",
    "veekunName": "harvest"
  },
  {
    "id": 140,
    "slug": "telepathy",
    "name": "Telepathy",
    "gen": 5,
    "rating": 0,
    "showdownName": "Telepathy",
    "veekunName": "telepathy"
  },
  {
    "id": 141,
    "slug": "moody",
    "name": "Moody",
    "gen": 5,
    "rating": 100,
    "showdownName": "Moody",
    "veekunName": "moody"
  },
  {
    "id": 142,
    "slug": "overcoat",
    "name": "Overcoat",
    "gen": 5,
    "rating": 40,
    "showdownName": "Overcoat",
    "veekunName": "overcoat"
  },
  {
    "id": 143,
    "slug": "poison-touch",
    "name": "Poison Touch",
    "gen": 5,
    "rating": 40,
    "showdownName": "Poison Touch",
    "veekunName": "poison-touch"
  },
  {
    "id": 144,
    "slug": "regenerator",
    "name": "Regenerator",
    "gen": 5,
    "rating": 90,
    "showdownName": "Regenerator",
    "veekunName": "regenerator"
  },
  {
    "id": 145,
    "slug": "big-pecks",
    "name": "Big Pecks",
    "gen": 5,
    "rating": 10,
    "showdownName": "Big Pecks",
    "veekunName": "big-pecks"
  },
  {
    "id": 146,
    "slug": "sand-rush",
    "name": "Sand Rush",
    "gen": 5,
    "rating": 60,
    "showdownName": "Sand Rush",
    "veekunName": "sand-rush"
  },
  {
    "id": 147,
    "slug": "wonder-skin",
    "name": "Wonder Skin",
    "gen": 5,
    "rating": 40,
    "showdownName": "Wonder Skin",
    "veekunName": "wonder-skin"
  },
  {
    "id": 148,
    "slug": "analytic",
    "name": "Analytic",
    "gen": 5,
    "rating": 50,
    "showdownName": "Analytic",
    "veekunName": "analytic"
  },
  {
    "id": 149,
    "slug": "illusion",
    "name": "Illusion",
    "gen": 5,
    "rating": 90,
    "showdownName": "Illusion",
    "veekunName": "illusion"
  },
  {
    "id": 150,
    "slug": "imposter",
    "name": "Imposter",
    "gen": 5,
    "rating": 100,
    "showdownName": "Imposter",
    "veekunName": "imposter"
  },
  {
    "id": 151,
    "slug": "infiltrator",
    "name": "Infiltrator",
    "gen": 5,
    "rating": 50,
    "showdownName": "Infiltrator",
    "veekunName": "infiltrator"
  },
  {
    "id": 152,
    "slug": "mummy",
    "name": "Mummy",
    "gen": 5,
    "rating": 40,
    "showdownName": "Mummy",
    "veekunName": "mummy"
  },
  {
    "id": 153,
    "slug": "moxie",
    "name": "Moxie",
    "gen": 5,
    "rating": 60,
    "showdownName": "Moxie",
    "veekunName": "moxie"
  },
  {
    "id": 154,
    "slug": "justified",
    "name": "Justified",
    "gen": 5,
    "rating": 50,
    "showdownName": "Justified",
    "veekunName": "justified"
  },
  {
    "id": 155,
    "slug": "rattled",
    "name": "Rattled",
    "gen": 5,
    "rating": 30,
    "showdownName": "Rattled",
    "veekunName": "rattled"
  },
  {
    "id": 156,
    "slug": "magic-bounce",
    "name": "Magic Bounce",
    "gen": 5,
    "rating": 80,
    "showdownName": "Magic Bounce",
    "veekunName": "magic-bounce"
  },
  {
    "id": 157,
    "slug": "sap-sipper",
    "name": "Sap Sipper",
    "gen": 5,
    "rating": 60,
    "showdownName": "Sap Sipper",
    "veekunName": "sap-sipper"
  },
  {
    "id": 158,
    "slug": "prankster",
    "name": "Prankster",
    "gen": 5,
    "rating": 80,
    "showdownName": "Prankster",
    "veekunName": "prankster"
  },
  {
    "id": 159,
    "slug": "sand-force",
    "name": "Sand Force",
    "gen": 5,
    "rating": 40,
    "showdownName": "Sand Force",
    "veekunName": "sand-force"
  },
  {
    "id": 160,
    "slug": "iron-barbs",
    "name": "Iron Barbs",
    "gen": 5,
    "rating": 50,
    "showdownName": "Iron Barbs",
    "veekunName": "iron-barbs"
  },
  {
    "id": 161,
    "slug": "zen-mode",
    "name": "Zen Mode",
    "gen": 5,
    "rating": 0,
    "showdownName": "Zen Mode",
    "veekunName": "zen-mode"
  },
  {
    "id": 162,
    "slug": "victory-star",
    "name": "Victory Star",
    "gen": 5,
    "rating": 40,
    "showdownName": "Victory Star",
    "veekunName": "victory-star"
  },
  {
    "id": 163,
    "slug": "turboblaze",
    "name": "Turboblaze",
    "gen": 5,
    "rating": 70,
    "showdownName": "Turboblaze",
    "veekunName": "turboblaze"
  },
  {
    "id": 164,
    "slug": "teravolt",
    "name": "Teravolt",
    "gen": 5,
    "rating": 70,
    "showdownName": "Teravolt",
    "veekunName": "teravolt"
  },
  {
    "id": 165,
    "slug": "aroma-veil",
    "name": "Aroma Veil",
    "gen": 6,
    "rating": 40,
    "showdownName": "Aroma Veil",
    "veekunName": "aroma-veil"
  },
  {
    "id": 166,
    "slug": "flower-veil",
    "name": "Flower Veil",
    "gen": 6,
    "rating": 0,
    "showdownName": "Flower Veil",
    "veekunName": "flower-veil"
  },
  {
    "id": 167,
    "slug": "cheek-pouch",
    "name": "Cheek Pouch",
    "gen": 6,
    "rating": 40,
    "showdownName": "Cheek Pouch",
    "veekunName": "cheek-pouch"
  },
  {
    "id": 168,
    "slug": "protean",
    "name": "Protean",
    "gen": 6,
    "rating": 90,
    "showdownName": "Protean",
    "veekunName": "protean"
  },
  {
    "id": 169,
    "slug": "fur-coat",
    "name": "Fur Coat",
    "gen": 6,
    "rating": 80,
    "showdownName": "Fur Coat",
    "veekunName": "fur-coat"
  },
  {
    "id": 170,
    "slug": "magician",
    "name": "Magician",
    "gen": 6,
    "rating": 30,
    "showdownName": "Magician",
    "veekunName": "magician"
  },
  {
    "id": 171,
    "slug": "bulletproof",
    "name": "Bulletproof",
    "gen": 6,
    "rating": 60,
    "showdownName": "Bulletproof",
    "veekunName": "bulletproof"
  },
  {
    "id": 172,
    "slug": "competitive",
    "name": "Competitive",
    "gen": 6,
    "rating": 50,
    "showdownName": "Competitive",
    "veekunName": "competitive"
  },
  {
    "id": 173,
    "slug": "strong-jaw",
    "name": "Strong Jaw",
    "gen": 6,
    "rating": 60,
    "showdownName": "Strong Jaw",
    "veekunName": "strong-jaw"
  },
  {
    "id": 174,
    "slug": "refrigerate",
    "name": "Refrigerate",
    "gen": 6,
    "rating": 80,
    "showdownName": "Refrigerate",
    "veekunName": "refrigerate"
  },
  {
    "id": 175,
    "slug": "sweet-veil",
    "name": "Sweet Veil",
    "gen": 6,
    "rating": 40,
    "showdownName": "Sweet Veil",
    "veekunName": "sweet-veil"
  },
  {
    "id": 176,
    "slug": "stance-change",
    "name": "Stance Change",
    "gen": 6,
    "rating": 80,
    "showdownName": "Stance Change",
    "veekunName": "stance-change"
  },
  {
    "id": 177,
    "slug": "gale-wings",
    "name": "Gale Wings",
    "gen": 6,
    "rating": 60,
    "showdownName": "Gale Wings",
    "veekunName": "gale-wings"
  },
  {
    "id": 178,
    "slug": "mega-launcher",
    "name": "Mega Launcher",
    "gen": 6,
    "rating": 60,
    "showdownName": "Mega Launcher",
    "veekunName": "mega-launcher"
  },
  {
    "id": 179,
    "slug": "grass-pelt",
    "name": "Grass Pelt",
    "gen": 6,
    "rating": 10,
    "showdownName": "Grass Pelt",
    "veekunName": "grass-pelt"
  },
  {
    "id": 180,
    "slug": "symbiosis",
    "name": "Symbiosis",
    "gen": 6,
    "rating": 0,
    "showdownName": "Symbiosis",
    "veekunName": "symbiosis"
  },
  {
    "id": 181,
    "slug": "tough-claws",
    "name": "Tough Claws",
    "gen": 6,
    "rating": 70,
    "showdownName": "Tough Claws",
    "veekunName": "tough-claws"
  },
  {
    "id": 182,
    "slug": "pixilate",
    "name": "Pixilate",
    "gen": 6,
    "rating": 80,
    "showdownName": "Pixilate",
    "veekunName": "pixilate"
  },
  {
    "id": 183,
    "slug": "gooey",
    "name": "Gooey",
    "gen": 6,
    "rating": 40,
    "showdownName": "Gooey",
    "veekunName": "gooey"
  },
  {
    "id": 184,
    "slug": "aerilate",
    "name": "Aerilate",
    "gen": 6,
    "rating": 80,
    "showdownName": "Aerilate",
    "veekunName": "aerilate"
  },
  {
    "id": 185,
    "slug": "parental-bond",
    "name": "Parental Bond",
    "gen": 6,
    "rating": 90,
    "showdownName": "Parental Bond",
    "veekunName": "parental-bond"
  },
  {
    "id": 186,
    "slug": "dark-aura",
    "name": "Dark Aura",
    "gen": 6,
    "rating": 60,
    "showdownName": "Dark Aura",
    "veekunName": "dark-aura"
  },
  {
    "id": 187,
    "slug": "fairy-aura",
    "name": "Fairy Aura",
    "gen": 6,
    "rating": 60,
    "showdownName": "Fairy Aura",
    "veekunName": "fairy-aura"
  },
  {
    "id": 188,
    "slug": "aura-break",
    "name": "Aura Break",
    "gen": 6,
    "rating": 20,
    "showdownName": "Aura Break",
    "veekunName": "aura-break"
  },
  {
    "id": 189,
    "slug": "primordial-sea",
    "name": "Primordial Sea",
    "gen": 6,
    "rating": 90,
    "showdownName": "Primordial Sea",
    "veekunName": "primordial-sea"
  },
  {
    "id": 190,
    "slug": "desolate-land",
    "name": "Desolate Land",
    "gen": 6,
    "rating": 90,
    "showdownName": "Desolate Land",
    "veekunName": "desolate-land"
  },
  {
    "id": 191,
    "slug": "delta-stream",
    "name": "Delta Stream",
    "gen": 6,
    "rating": 80,
    "showdownName": "Delta Stream",
    "veekunName": "delta-stream"
  }
]
